{
  "filename": "table_002_665.png",
  "file_path": "C:\\Users\\tel33\\OneDrive\\바탕 화면\\2025년 하계방학\\7월 인턴 넥스제너\\codes\\ddd\\Medical_pdf_parsing_PR\\output_data\\uploaded_files\\「의약품의+시판+후+정기적인+안전성정보+보고+검토지침(공무원지침서)」_본문\\tables\\table_002_665.png",
  "page_number": 2,
  "region": {
    "x": "531",
    "y": "2406",
    "width": "1349",
    "height": "172"
  },
  "table_data": {
    "type": "simple_table",
    "rows": 16,
    "columns": 3,
    "cells": [
      [
        557,
        121,
        27,
        16
      ],
      [
        717,
        120,
        27,
        16
      ],
      [
        236,
        120,
        29,
        17
      ],
      [
        393,
        107,
        22,
        19
      ],
      [
        599,
        97,
        22,
        29
      ],
      [
        508,
        97,
        19,
        28
      ],
      [
        298,
        96,
        41,
        41
      ],
      [
        97,
        96,
        20,
        21
      ],
      [
        668,
        95,
        22,
        21
      ],
      [
        187,
        95,
        23,
        22
      ],
      [
        144,
        95,
        21,
        16
      ],
      [
        833,
        94,
        10,
        43
      ],
      [
        789,
        94,
        4,
        43
      ],
      [
        550,
        94,
        41,
        24
      ],
      [
        529,
        94,
        13,
        43
      ],
      [
        236,
        94,
        28,
        15
      ],
      [
        162,
        94,
        13,
        34
      ],
      [
        831,
        57,
        29,
        16
      ],
      [
        260,
        57,
        29,
        15
      ],
      [
        305,
        56,
        28,
        17
      ],
      [
        98,
        56,
        29,
        17
      ],
      [
        1037,
        55,
        29,
        17
      ],
      [
        420,
        55,
        28,
        18
      ],
      [
        948,
        54,
        28,
        18
      ],
      [
        376,
        54,
        28,
        18
      ],
      [
        216,
        54,
        26,
        18
      ],
      [
        138,
        53,
        30,
        19
      ],
      [
        1125,
        43,
        22,
        19
      ],
      [
        461,
        43,
        22,
        19
      ],
      [
        1076,
        41,
        29,
        25
      ],
      [
        26,
        37,
        35,
        36
      ],
      [
        1169,
        34,
        22,
        29
      ],
      [
        780,
        33,
        21,
        30
      ],
      [
        619,
        33,
        40,
        34
      ],
      [
        574,
        33,
        21,
        30
      ],
      [
        1032,
        32,
        21,
        23
      ],
      [
        733,
        32,
        41,
        41
      ],
      [
        257,
        32,
        19,
        22
      ],
      [
        416,
        31,
        22,
        19
      ],
      [
        370,
        31,
        22,
        20
      ],
      [
        142,
        31,
        22,
        18
      ],
      [
        1244,
        30,
        11,
        43
      ],
      [
        1190,
        30,
        14,
        43
      ],
      [
        831,
        30,
        29,
        16
      ],
      [
        671,
        30,
        28,
        18
      ],
      [
        598,
        30,
        12,
        43
      ],
      [
        507,
        30,
        33,
        43
      ],
      [
        305,
        30,
        27,
        15
      ],
      [
        211,
        30,
        31,
        22
      ]
    ],
    "image_shape": [
      172,
      1349,
      3
    ]
  },
  "extraction_method": "OpenCV_contour_detection"
}